README.txt
setup.py
smarttap/Analysis_Module.py
smarttap/DB_Module.py
smarttap/GUI_Module.py
smarttap/Input_Module.py
smarttap/Management_Module.py
smarttap/Raw_Module.py
smarttap/__init__.py
smarttap.egg-info/PKG-INFO
smarttap.egg-info/SOURCES.txt
smarttap.egg-info/dependency_links.txt
smarttap.egg-info/requires.txt
smarttap.egg-info/top_level.txt