Metadata-Version: 1.1
Name: smarttap
Version: 1.0.0
Summary: Public transport smart card data analysis software
Home-page: https://github.com/JohnTasker/SmartTAP
Author: John Tasker
Author-email: john.tasler@uq.edu.au
License: GNU GPL V3
Platform: UNKNOWN
Classifier: Development Status :: 5 - Production/Stable
Classifier: Intended Audience :: Science/Research
Classifier: Topic :: Scientific/Engineering :: Information Analysis
Classifier: Topic :: Scientific/Engineering :: GIS
Classifier: License :: OSI Approved :: GNU General Public License v3 (GPLv3)
Classifier: Programming Language :: Python :: 3
Classifier: Programming Language :: Python :: 3.2
Classifier: Programming Language :: Python :: 3.3
Classifier: Programming Language :: Python :: 3.4
Classifier: Programming Language :: Python :: 3.5
